firelight/__init__.py
firelight/config_parsing.py
firelight/inferno_callback.py
firelight/examples/__init__.py
firelight/examples/example_data.py
firelight/examples/test.py
firelight/utils/__init__.py
firelight/utils/dim_utils.py
firelight/utils/io_utils.py
firelight/visualizers/__init__.py
firelight/visualizers/base.py
firelight/visualizers/colorization.py
firelight/visualizers/container_visualizers.py
firelight/visualizers/visualizers.py
firelight-0.2.1.dist-info/LICENSE
firelight-0.2.1.dist-info/METADATA
firelight-0.2.1.dist-info/WHEEL
firelight-0.2.1.dist-info/top_level.txt
firelight-0.2.1.dist-info/RECORD
