Metadata-Version: 2.1
Name: firelight
Version: 0.2.1
Summary: A visualization library for PyTorch tensors.
Home-page: https://github.com/inferno-pytorch/firelight
Author: Roman Remme
Author-email: roman.remme@iwr.uni-heidelberg.de
License: Apache Software License 2.0
Platform: UNKNOWN
Classifier: Intended Audience :: Science/Research
Classifier: Programming Language :: Python :: 3
Classifier: License :: OSI Approved :: Apache Software License
Requires-Dist: pyyaml (>=3.12)
Requires-Dist: matplotlib
Requires-Dist: numpy
Requires-Dist: scikit-learn
Requires-Dist: scikit-image
Requires-Dist: torch
